{"nodes": [{"id": "e_aitradra_ui_src_components_diagnosticview_jsx", "label": "DiagnosticView.jsx", "file_type": "code", "source_file": "E:\\AITradra\\ui\\src\\components\\DiagnosticView.jsx", "source_location": "L1"}, {"id": "diagnosticview_diagnosticview", "label": "DiagnosticView()", "file_type": "code", "source_file": "E:\\AITradra\\ui\\src\\components\\DiagnosticView.jsx", "source_location": "L4"}], "edges": [{"source": "e_aitradra_ui_src_components_diagnosticview_jsx", "target": "react", "relation": "imports_from", "confidence": "EXTRACTED", "source_file": "E:\\AITradra\\ui\\src\\components\\DiagnosticView.jsx", "source_location": "L1", "weight": 1.0}, {"source": "e_aitradra_ui_src_components_diagnosticview_jsx", "target": "lucide_react", "relation": "imports_from", "confidence": "EXTRACTED", "source_file": "E:\\AITradra\\ui\\src\\components\\DiagnosticView.jsx", "source_location": "L2", "weight": 1.0}, {"source": "e_aitradra_ui_src_components_diagnosticview_jsx", "target": "diagnosticview_diagnosticview", "relation": "contains", "confidence": "EXTRACTED", "source_file": "E:\\AITradra\\ui\\src\\components\\DiagnosticView.jsx", "source_location": "L4", "weight": 1.0}], "raw_calls": [{"caller_nid": "diagnosticview_diagnosticview", "callee": "filter", "source_file": "E:\\AITradra\\ui\\src\\components\\DiagnosticView.jsx", "source_location": "L5"}, {"caller_nid": "diagnosticview_diagnosticview", "callee": "map", "source_file": "E:\\AITradra\\ui\\src\\components\\DiagnosticView.jsx", "source_location": "L11"}, {"caller_nid": "diagnosticview_diagnosticview", "callee": "map", "source_file": "E:\\AITradra\\ui\\src\\components\\DiagnosticView.jsx", "source_location": "L28"}]}